fecfile/__init__.py
fecfile/cache.py
fecfile/fecparser.py
fecfile/mappings.json
fecfile/types.json
fecfile-0.9.1.dist-info/licenses/LICENSE
fecfile-0.9.1.dist-info/METADATA
fecfile-0.9.1.dist-info/WHEEL
fecfile-0.9.1.dist-info/top_level.txt
fecfile-0.9.1.dist-info/RECORD
