Metadata-Version: 2.4
Name: fecfile
Version: 0.9.1
Summary: a python parser for the .fec file format
Home-page: https://esonderegger.github.io/fecfile/
Author: Evan Sonderegger
Author-email: evan@rpy.xyz
License: Apache License 2.0
Project-URL: Bug Tracker, https://github.com/esonderegger/fecfile/issues
Project-URL: Source Code, https://github.com/esonderegger/fecfile/
Keywords: fec campaign finance politics
Classifier: Development Status :: 3 - Alpha
Classifier: Environment :: Console
Classifier: Intended Audience :: Developers
Classifier: License :: OSI Approved :: Apache Software License
Classifier: Operating System :: OS Independent
Classifier: Programming Language :: Python
License-File: LICENSE
Requires-Dist: pytz>=2018.4
Requires-Dist: requests>=2.19.1
Dynamic: author
Dynamic: author-email
Dynamic: classifier
Dynamic: description
Dynamic: description-content-type
Dynamic: home-page
Dynamic: keywords
Dynamic: license
Dynamic: license-file
Dynamic: project-url
Dynamic: requires-dist
Dynamic: summary
